peach_invasion/__init__.py
peach_invasion/main.py
peach_invasion/settings.py
peach_invasion/game_objects/__init__.py
peach_invasion/game_objects/bullet.py
peach_invasion/game_objects/enemy.py
peach_invasion/game_objects/object.py
peach_invasion/game_objects/player.py
peach_invasion/movement/__init__.py
peach_invasion/movement/falling_sideways.py
peach_invasion/movement/falling_sideways_shaking.py
peach_invasion/movement/scheme.py
peach_invasion/static/audio/background.wav
peach_invasion/static/audio/death.wav
peach_invasion/static/audio/enemy_death_1.ogg
peach_invasion/static/audio/enemy_death_2.wav
peach_invasion/static/audio/enemy_death_3.wav
peach_invasion/static/audio/enemy_death_4.wav
peach_invasion/static/audio/enemy_death_5.wav
peach_invasion/static/audio/fire.wav
peach_invasion/static/audio/no_ammo.wav
peach_invasion/static/audio/victory.ogg
peach_invasion/static/images/ammo.bmp
peach_invasion/static/images/bullet.bmp
peach_invasion/static/images/enemy.bmp
peach_invasion/static/images/grass.bmp
peach_invasion/static/images/health.bmp
peach_invasion/static/images/player.bmp
peach_invasion/static/images/screenshot.png
peach_invasion/ui/__init__.py
peach_invasion/ui/background.py
peach_invasion/ui/button.py
peach_invasion/ui/scoreboard.py
peach_invasion/ui/sound.py
peach_invasion/ui/stats.py
peach_invasion-0.1.0.dist-info/LICENSE
peach_invasion-0.1.0.dist-info/METADATA
peach_invasion-0.1.0.dist-info/WHEEL
peach_invasion-0.1.0.dist-info/entry_points.txt
peach_invasion-0.1.0.dist-info/top_level.txt
peach_invasion-0.1.0.dist-info/RECORD
