Metadata-Version: 2.1
Name: peach-invasion
Version: 0.1.0
Summary: Peach invasion 2D game with pygame
Home-page: https://github.com/olbed/peach_invasion
Author: olbed
License: UNKNOWN
Platform: UNKNOWN
Requires-Dist: pygame (<2,>=1.9.6)
